{
  "crawled_at": "2026-06-03T22:37:03",
  "source_url": "https://www.agoda.com/sunlight-hotel-h51568479/hotel/gia-lam-vn.html?hotel=51568479&currency=VND&checkIn=2026-06-13&checkOut=2026-06-14&rooms=1&adults=2&children=0",
  "hotel_id": 51568479,
  "name": "Sunlight Condotel Hà Nội (Sunlight Condotel Hanoi)",
  "property_type": "Hotel",
  "accommodation_type": "Khách sạn",
  "star_rating": 5.0,
  "is_luxury": false,
  "gold_circle_award_year": null,
  "review_score": 8.9,
  "review_count": 101,
  "address": "Masteri Waterfront M3, Vinhomes Ocean Park, Đa Tốn, Gia L m, Hanoi, Vietnam, Đa Tốn, Gia Lâm, Việt Nam",
  "area": "Đa Tốn",
  "city": "Gia Lâm",
  "country": "Việt Nam",
  "postal_code": "100000",
  "latitude": 20.99254035949707,
  "longitude": 105.94457244873047,
  "description": "Khám Phá Sự Sang Trọng Tại Sunlight Condotel Hanoi - Địa Điểm 5 Sao Tại Gia Lâm\n\nSunlight Condotel Hanoi là một khách sạn 5 sao đẳng cấp nằm tại trung tâm khu vực Gia Lâm, Việt Nam, mang đến trải nghiệm lưu trú sang trọng và tiện nghi cho mọi du khách. Với thời gian nhận phòng bắt đầu từ 14:00 và trả phòng vào lúc 12:00 trưa, khách hàng có thể thoải mái tận hưởng kỳ nghỉ của mình mà không cần lo lắng về thủ tục. Khách sạn chỉ có một phòng duy nhất, mang lại cảm giác riêng tư và đẳng cấp cho mỗi khách lưu trú.\n\nĐặc biệt, Sunlight Condotel Hanoi có chính sách thân thiện với gia đình, cho phép trẻ em từ 1 đến 2 tuổi ở miễn phí. Đây là lựa chọn lý tưởng cho các gia đình muốn kết hợp sự sang trọng và sự thoải mái trong chuyến đi của mình. Với dịch vụ tuyệt vời và không gian tinh tế, khách sạn chắc chắn sẽ để lại ấn tượng khó quên trong lòng mỗi du khách khi ghé thăm Gia Lâm.\n\nTiện Nghi Giải Trí Đẳng Cấp Tại Sunlight Condotel Hanoi\n\nTại Sunlight Condotel Hanoi, du khách sẽ được trải nghiệm một loạt các tiện ích giải trí đa dạng và phong phú để thư giãn và tận hưởng kỳ nghỉ của mình. Khu vườn xinh đẹp mang lại không gian yên bình, lý tưởng để thư giãn hoặc tận hưởng những buổi sáng sớm trong lành. Ngoài ra, khu vực lounge chung cùng phòng xem TV giúp khách có thể giao lưu và thư giãn cùng nhau sau một ngày khám phá thành phố. Đối với những ai yêu thích giải trí âm nhạc, dịch vụ karaoke sôi động sẽ mang lại những phút giây vui vẻ và gắn kết bên bạn bè và người thân.\n\nKhông chỉ dừng lại ở đó, Sunlight Condotel Hanoi còn cung cấp các tiện ích mua sắm như cửa hàng quà lưu niệm và cửa hàng đặc sản, giúp du khách dễ dàng tìm kiếm những món quà ý nghĩa để tặng người thân. Dịch vụ salon, massage và spa cao cấp mang đến trải nghiệm làm đẹp và thư giãn tuyệt vời, giúp khách lấy lại năng lượng sau những ngày dài di chuyển hoặc công tác. Tất cả những tiện ích này đều nhằm mang đến cho du khách một kỳ nghỉ trọn vẹn, thoải mái và đầy sắc màu tại trung tâm Gia Lâm.\n\nTiện Nghi Thể Thao Đa Dạng Tại Sunlight Condotel Hanoi\n\nTại Sunlight Condotel Hanoi, du khách sẽ được trải nghiệm một loạt các tiện nghi thể thao đẳng cấp để duy trì phong độ và thư giãn sau những giờ phút khám phá thành phố. Khách sạn sở hữu trung tâm thể hình hiện đại, giúp bạn duy trì lối sống năng động và khỏe mạnh. Ngoài ra, các hoạt động thể thao ngoài trời như sân tennis, sân bóng bàn, sân cầu lông và sân mini golf mang đến những trải nghiệm vui vẻ và sôi động cho cả gia đình và nhóm bạn. Đối với những ai yêu thích hoạt động dưới nước, hồ bơi trong nhà và hồ bơi ngoài trời với quầy bar bên hồ là nơi lý tưởng để thư giãn và thưởng thức không khí trong lành.\n\nKhông chỉ dừng lại ở đó, Sunlight Condotel Hanoi còn có sân golf ngay tại chỗ, khu vực câu cá, khu vui chơi nước, và phòng yoga yên tĩnh giúp bạn cân bằng giữa thể chất và tinh thần. Với các tiện ích đa dạng này, du khách có thể dễ dàng lựa chọn hoạt động phù hợp để nâng cao sức khỏe, giải trí hoặc thư giãn, mang lại trải nghiệm hoàn hảo trong suốt kỳ nghỉ của mình.\n\nTiện Nghi Tiện Lợi Tại Sunlight Condotel Hanoi\n\nSunlight Condotel Hanoi mang đến cho khách lưu trú những tiện ích hiện đại và tiện nghi để đảm bảo trải nghiệm thoải mái nhất. Khách hàng có thể tận hưởng dịch vụ Wi-Fi miễn phí trong tất cả các phòng, giúp dễ dàng kết nối và làm việc suốt ngày. Đặc biệt, khách còn được sử dụng dịch vụ check-in và check-out nhanh chóng, tiết kiệm thời gian và thuận tiện cho lịch trình di chuyển. Ngoài ra, khách còn có thể dễ dàng mua sắm tại cửa hàng tiện lợi ngay trong khuôn viên khách sạn hoặc sử dụng dịch vụ giặt ủi hàng ngày để giữ gìn quần áo luôn sạch sẽ và mới mẻ. Đối với những người hút thuốc, Sunlight Condotel Hanoi còn có khu vực hút thuốc riêng biệt, đảm bảo vệ sinh và an toàn cho toàn bộ khách lưu trú.\n\nTiện Nghi Giao Thông Tại Sunlight Condotel Hanoi\n\nTại Sunlight Condotel Hanoi, khách lưu trú sẽ được trải nghiệm dịch vụ đỗ xe tiện lợi và an toàn ngay trong khuôn viên khách sạn. Với khu vực đỗ xe nằm ngay tại chỗ, khách có thể yên tâm về sự thuận tiện trong việc di chuyển và lưu giữ phương tiện của mình. Dịch vụ đỗ xe tự phục vụ giúp khách hàng dễ dàng tiếp cận và sử dụng theo ý muốn của mình, mang lại cảm giác thoải mái và linh hoạt trong suốt kỳ nghỉ.\n\nĐặc biệt, khách lưu trú tại đây còn được hưởng dịch vụ đỗ xe miễn phí, giúp tiết kiệm chi phí và tăng thêm phần tiện nghi cho chuyến đi. Trong trường hợp cần thiết, khách cũng có thể sử dụng các dịch vụ đỗ xe có phí, phù hợp với nhu cầu và lịch trình của từng người. Với hệ thống giao thông thuận tiện và các tiện ích đỗ xe đa dạng, Sunlight Condotel Hanoi cam kết mang lại trải nghiệm lưu trú trọn vẹn, dễ dàng di chuyển và thuận tiện tối đa cho khách hàng.\n\nTiện nghi phòng ốc hiện đại tại Sunlight Condotel Hanoi\n\nTại Sunlight Condotel Hanoi, khách lưu trú sẽ được trải nghiệm không gian nghỉ dưỡng tiện nghi với đầy đủ các thiết bị cao cấp. Phòng có điều hòa không khí giúp duy trì nhiệt độ lý tưởng, cùng với rèm chắn sáng giúp tạo không gian yên tĩnh, thoải mái. Khách còn có thể thư giãn với các bộ phim trong nhà qua hệ thống truyền hình, hoặc tận hưởng không khí trong lành từ ban công hoặc sân thượng riêng biệt.\n\nNgoài ra, các tiện ích như máy sấy tóc, đồ dùng vệ sinh cá nhân, nước khoáng miễn phí, tủ lạnh, và trà, cà phê miễn phí mang đến sự tiện lợi tối đa. Phòng còn có phòng khách riêng biệt, giúp khách có không gian sinh hoạt rộng rãi, thoải mái. Đặc biệt, các bộ đồ tắm, áo choàng tắm sang trọng và các tiện nghi khác sẽ làm cho kỳ nghỉ của bạn thêm phần trọn vẹn, thư giãn.\n\nTiện Nghi Ẩm Thực Tại Sunlight Condotel Hanoi\n\nTại Sunlight Condotel Hanoi, du khách sẽ được trải nghiệm dịch vụ ẩm thực đa dạng và tiện nghi, trong đó nổi bật là các khu vực BBQ hiện đại, lý tưởng để tổ chức những buổi tiệc ngoài trời ấm cúng cùng gia đình hoặc bạn bè. Không khí trong lành và không gian thoáng đãng của khu vực BBQ giúp bạn thưởng thức những món nướng thơm ngon, đậm đà trong khung cảnh thiên nhiên yên bình của Gia Lâm. Ngoài ra, khách sạn còn cung cấp dịch vụ dọn dẹp hàng ngày, đảm bảo không gian luôn sạch sẽ, gọn gàng để du khách có thể hoàn toàn thư giãn và tận hưởng kỳ nghỉ của mình một cách trọn vẹn nhất.\n\nCác Loại Phòng Tại Sunlight Condotel Hanoi - Sự Lựa Chọn Hoàn Hảo Cho Kỳ Nghỉ Của Bạn\n\nTại Sunlight Condotel Hanoi, bạn có thể lựa chọn phòng TWIN rộng 32 mét vuông, được trang bị hai giường đơn phù hợp cho những khách du lịch đi cùng bạn bè hoặc gia đình nhỏ. Phòng TWIN mang đến không gian thoải mái, tiện nghi để bạn thư giãn và tận hưởng kỳ nghỉ của mình một cách trọn vẹn. Mỗi phòng đều được thiết kế tinh tế, mang lại cảm giác ấm cúng và thân thiện, giúp bạn cảm thấy như đang ở nhà ngay trong chuyến đi xa nhà.\n\nKhi đặt phòng qua Agoda, bạn sẽ nhận được mức giá tốt nhất cùng với quy trình đặt phòng nhanh chóng, dễ dàng và không gây phiền hà. Các ưu đãi hấp dẫn này giúp bạn tiết kiệm chi phí và có thêm thời gian để tận hưởng những trải nghiệm tuyệt vời tại Gia Lâm. Đặt phòng ngay hôm nay để đảm bảo chuyến đi của bạn không chỉ trọn vẹn mà còn thuận tiện nhất!\n\nKhám Phá Vùng Đất Đa Tốn - Gia Lâm, Hà Nội\n\nĐa Tốn, một xã thuộc huyện Gia Lâm, Hà Nội, nổi bật với vẻ đẹp bình yên và phong cảnh thiên nhiên tươi đẹp. Nơi đây mang đậm nét truyền thống Việt Nam với những cánh đồng lúa xanh mướt, những con sông nhỏ uốn lượn qua làng quê thanh bình. Du khách có thể tận hưởng không khí trong lành, thư thái và cảm nhận rõ nét nét đẹp của cuộc sống nông thôn chân thực, mộc mạc.\nNgoài ra, Đa Tốn còn gần kề nhiều điểm tham quan hấp dẫn như các làng nghề truyền thống, các chợ địa phương sôi động và những di tích lịch sử nhỏ nhưng ý nghĩa. Vùng đất này còn là nơi lý tưởng để trải nghiệm các hoạt động ngoài trời như đi bộ đường dài, câu cá hoặc thưởng thức ẩm thực đặc sản địa phương. Đến với Đa Tốn, du khách không chỉ được thư giãn mà còn có cơ hội khám phá nét đẹp văn hóa và cuộc sống bình dị nhưng đầy sức sống của vùng quê Hà Nội.\n\nHướng Dẫn Di Chuyển Từ Sân Bay Đến Sunlight Condotel Hanoi Tại Gia Lâm\n\nTừ sân bay Nội Bài, khách du lịch có nhiều lựa chọn để đến với Sunlight Condotel Hanoi tại Đa Tốn, Gia Lâm. Nếu bạn muốn di chuyển nhanh chóng và tiện lợi, dịch vụ taxi hoặc xe đưa đón riêng là lựa chọn hàng đầu, chỉ mất khoảng 30-40 phút tùy vào tình hình giao thông. Bạn có thể dễ dàng bắt taxi ngay tại khu vực nhà ga hoặc đặt dịch vụ xe đưa đón trước để đảm bảo có phương tiện sẵn sàng chờ đón khi bạn đến nơi. Ngoài ra, nếu muốn tiết kiệm hơn, bạn có thể sử dụng các dịch vụ xe buýt liên tỉnh hoặc xe khách, sau đó chuyển sang taxi hoặc xe công cộng để đến địa chỉ mong muốn.\n\nKết hợp các phương tiện công cộng như xe buýt cũng là một lựa chọn phù hợp cho những ai thích khám phá và tiết kiệm chi phí. Từ sân bay Nội Bài, bạn có thể bắt tuyến xe buýt số 86 hoặc 07 đến trung tâm Gia Lâm, rồi tiếp tục di chuyển bằng taxi hoặc xe máy thuê để đến Sunlight Condotel. Dù lựa chọn phương tiện nào, hành trình từ sân bay đến khách sạn đều khá dễ dàng, giúp bạn bắt đầu chuyến đi của mình một cách thuận tiện và thoải mái.\n\nGiá phòng tại Sunlight Condotel Hanoi - Cạnh tranh và hợp lý trong khu vực\n\nSunlight Condotel Hanoi mang đến mức giá phòng vô cùng hấp dẫn, dao động từ 26 đến 50 USD mỗi đêm, phù hợp với ngân sách của nhiều du khách. Với mức giá này, khách hàng có thể tận hưởng không gian nghỉ dưỡng tiện nghi, thoải mái mà không phải lo lắng về chi phí quá cao. Điều đặc biệt là giá phòng của Sunlight Condotel Hanoi hoàn toàn cạnh tranh so với mức trung bình của khu vực Gia Lâm, nơi mà giá phòng khách sạn cũng nằm trong khoảng từ 26 đến 50 USD. Như vậy, du khách có thể yên tâm lựa chọn nơi lưu trú phù hợp với ngân sách, đồng thời trải nghiệm dịch vụ chất lượng cao tại một trong những khu vực đang phát triển của Hà Nội.\n\nĐánh giá tích cực về Sunlight Condotel Hanoi từ khách hàng\n\nSunlight Condotel Hanoi nhận được những đánh giá rất tích cực từ khách hàng, với điểm số tổng thể ấn tượng 9.3 trên nhiều khía cạnh. Khách lưu trú đặc biệt ấn tượng với chất lượng dịch vụ và tiện nghi tại khách sạn, khi các tiện ích hiện đại và đầy đủ mang lại sự hài lòng tối đa. Đặc biệt, mức độ sạch sẽ tại đây đạt điểm tuyệt đối 10.0, thể hiện cam kết của khách sạn trong việc duy trì môi trường trong lành và sạch sẽ cho khách hàng.\n\nVị trí của Sunlight Condotel Hanoi cũng được đánh giá cao, thuận tiện để khám phá các điểm tham quan nổi bật quanh khu vực. Giá trị mà khách sạn mang lại được khách hàng đánh giá rất cao, với điểm số 9.3 cho giá trị, cho thấy đây là lựa chọn hợp lý về mặt tài chính mà vẫn đảm bảo trải nghiệm tốt nhất. Dù có một số điểm cần cải thiện như hiệu suất làm việc của nhân viên, tổng thể, khách hàng đều hài lòng và đánh giá cao chất lượng dịch vụ tại đây, khiến đây trở thành một điểm đến lý tưởng cho chuyến đi của bạn tại Gia Lâm, Hà Nội.",
  "check_in_from": "14:00",
  "check_out_until": "12:00",
  "year_built": null,
  "number_of_floors": null,
  "number_of_rooms": "1",
  "useful_info": {
    "Nhận phòng từ": "14:00",
    "Trả phòng đến": "12:00",
    "Trả phòng từ": "12:00",
    "Nhận phòng đến": "21:00",
    "Số lượng phòng": "1"
  },
  "highlights": [
    "Wi-Fi miễn phí trong tất cả các phòng!",
    "Dọn phòng hằng ngày",
    "Quán bar cạnh bể bơi",
    "Rút tiền mặt",
    "Nhận/trả phòng [nhanh]"
  ],
  "location_tags": [
    "Bàn tiếp tân [24 giờ]",
    "Dọn phòng hằng ngày",
    "Quán bar cạnh bể bơi",
    "Thích hợp cho các hoạt động",
    "Wi-Fi miễn phí trong tất cả các phòng!"
  ],
  "amenities": [
    "Bi-a",
    "Bàn tiếp tân 24 giờ",
    "Bãi chơi bowling",
    "Bãi đậu xe tính phí",
    "Bảo vệ 24 giờ",
    "Bếp",
    "Bếp nhỏ",
    "Bể bơi có tầm nhìn",
    "Bể bơi ngoài trời",
    "Bể bơi trong nhà",
    "Bể bơi trẻ em",
    "Bệnh xá",
    "CCTV trong khu vực chung",
    "CLB trẻ em",
    "Câu cá",
    "Có cung cấp hóa đơn",
    "Công viên nước",
    "Cửa hàng quà tặng quà lưu niệm",
    "Cửa hàng tạp hóa",
    "Dịch vụ bưu chính",
    "Dịch vụ thanh toán không sử dụng tiền mặt",
    "Dọn phòng hằng ngày",
    "Giải trí",
    "Hành lang ngoài",
    "Hộp vệ sinh cho mèo",
    "Karaoke",
    "Khu vực hút thuốc",
    "Mát-xa",
    "Nhận trả phòng không tiếp xúc",
    "Nhận trả phòng nhanh",
    "Phòng chờ chung khu vực tv",
    "Phòng có gương",
    "Phòng gia đình",
    "Phòng hai tầng",
    "Phòng không gây dị ứng",
    "Phòng máy giặt tự động",
    "Phòng theo chủ đề",
    "Phòng tập",
    "Phòng yoga",
    "Phòng được vệ sinh giữa các lần ở",
    "Quán bar cạnh bể bơi",
    "Rút tiền mặt",
    "Spa xông khô",
    "Sân bóng quần",
    "Sân chơi",
    "Sân cầu lông",
    "Sân gôn",
    "Sân gôn nhỏ",
    "Sân gôn tại chỗ nghỉ",
    "Sân hiên",
    "Sân quần vợt",
    "Thang máy",
    "Thuê xe đạp",
    "Thích hợp cho gia đình trẻ em",
    "Tiếng Anh",
    "Tiếng Việt",
    "Tiệm làm đẹp",
    "Tiện nghi bể bơi",
    "Tiện nghi nấu nướng ngoài trời",
    "Toàn bộ nhà",
    "Trung Quốc quảng đông",
    "Trạm sạc điện xe hơi",
    "Tính năng an toàn bảo mật",
    "Vườn",
    "WiFi miễn phí",
    "Đỗ xe gần bên",
    "Đỗ xe miễn phí",
    "Đỗ xe tại chỗ"
  ],
  "amenities_count": 74,
  "amenity_groups": {
    "Tiện nghi phổ biến": [
      "Bếp",
      "Phòng tập"
    ],
    "Ngôn ngữ được sử dụng": [
      "Tiếng Anh",
      "Tiếng Việt",
      "Trung Quốc quảng đông"
    ],
    "Truy cập Internet": [
      "WiFi miễn phí"
    ],
    "Thư giãn & Vui chơi giải trí": [
      "Bi-a",
      "Bãi chơi bowling",
      "Bể bơi có tầm nhìn",
      "Bể bơi ngoài trời",
      "Bể bơi trong nhà",
      "Câu cá",
      "Công viên nước",
      "Giải trí",
      "Karaoke",
      "Mát-xa",
      "Phòng tập",
      "Phòng yoga",
      "Spa xông khô",
      "Sân bóng quần",
      "Sân cầu lông",
      "Sân gôn nhỏ",
      "Sân gôn tại chỗ nghỉ",
      "Sân quần vợt",
      "Tiện nghi bể bơi",
      "Vườn"
    ],
    "Độ sạch sẽ và an toàn": [
      "Dịch vụ thanh toán không sử dụng tiền mặt",
      "Phòng được vệ sinh giữa các lần ở"
    ],
    "Ăn uống": [
      "Bếp",
      "Bếp nhỏ",
      "Quán bar cạnh bể bơi",
      "Tiện nghi nấu nướng ngoài trời"
    ],
    "Dịch vụ và tiện nghi": [
      "Bệnh xá",
      "Có cung cấp hóa đơn",
      "Cửa hàng quà tặng quà lưu niệm",
      "Cửa hàng tạp hóa",
      "Dịch vụ bưu chính",
      "Dọn phòng hằng ngày",
      "Khu vực hút thuốc",
      "Nhận trả phòng không tiếp xúc",
      "Phòng chờ chung khu vực tv",
      "Phòng máy giặt tự động",
      "Rút tiền mặt",
      "Sân hiên",
      "Thang máy",
      "Tiệm làm đẹp"
    ],
    "Dành cho trẻ em": [
      "Bể bơi trẻ em",
      "CLB trẻ em",
      "Phòng gia đình",
      "Sân chơi",
      "Thích hợp cho gia đình trẻ em"
    ],
    "Hoạt động thể thao trên cạn ": [
      "Sân gôn"
    ],
    "Dễ dàng tiếp cận": [
      "Bàn tiếp tân 24 giờ",
      "Bảo vệ 24 giờ",
      "CCTV trong khu vực chung",
      "Hành lang ngoài",
      "Hộp vệ sinh cho mèo",
      "Nhận trả phòng nhanh",
      "Phòng có gương",
      "Phòng hai tầng",
      "Phòng không gây dị ứng",
      "Phòng theo chủ đề",
      "Toàn bộ nhà",
      "Tính năng an toàn bảo mật"
    ],
    "Đi lại": [
      "Bãi đậu xe tính phí",
      "Trạm sạc điện xe hơi",
      "Đỗ xe gần bên",
      "Đỗ xe miễn phí",
      "Đỗ xe tại chỗ"
    ],
    "Cho thuê dụng cụ thể thao": [
      "Thuê xe đạp"
    ]
  },
  "amenities_general": [
    "Bàn tiếp tân 24 giờ",
    "Bãi đậu xe tính phí",
    "Bảo vệ 24 giờ",
    "Bếp",
    "Bể bơi trẻ em",
    "Bệnh xá",
    "CCTV trong khu vực chung",
    "CLB trẻ em",
    "Có cung cấp hóa đơn",
    "Cửa hàng quà tặng quà lưu niệm",
    "Cửa hàng tạp hóa",
    "Dịch vụ bưu chính",
    "Dịch vụ thanh toán không sử dụng tiền mặt",
    "Dọn phòng hằng ngày",
    "Hành lang ngoài",
    "Hộp vệ sinh cho mèo",
    "Khu vực hút thuốc",
    "Nhận trả phòng không tiếp xúc",
    "Nhận trả phòng nhanh",
    "Phòng chờ chung khu vực tv",
    "Phòng có gương",
    "Phòng gia đình",
    "Phòng hai tầng",
    "Phòng không gây dị ứng",
    "Phòng máy giặt tự động",
    "Phòng theo chủ đề",
    "Phòng tập",
    "Phòng được vệ sinh giữa các lần ở",
    "Rút tiền mặt",
    "Sân chơi",
    "Sân hiên",
    "Thang máy",
    "Thích hợp cho gia đình trẻ em",
    "Tiếng Anh",
    "Tiếng Việt",
    "Tiệm làm đẹp",
    "Toàn bộ nhà",
    "Trung Quốc quảng đông",
    "Trạm sạc điện xe hơi",
    "Tính năng an toàn bảo mật",
    "WiFi miễn phí",
    "Đỗ xe gần bên",
    "Đỗ xe miễn phí",
    "Đỗ xe tại chỗ"
  ],
  "amenities_leisure": [
    "Bi-a",
    "Bãi chơi bowling",
    "Bể bơi có tầm nhìn",
    "Bể bơi ngoài trời",
    "Bể bơi trong nhà",
    "Câu cá",
    "Công viên nước",
    "Giải trí",
    "Karaoke",
    "Mát-xa",
    "Phòng tập",
    "Phòng yoga",
    "Spa xông khô",
    "Sân bóng quần",
    "Sân cầu lông",
    "Sân gôn",
    "Sân gôn nhỏ",
    "Sân gôn tại chỗ nghỉ",
    "Sân quần vợt",
    "Thuê xe đạp",
    "Tiện nghi bể bơi",
    "Vườn"
  ],
  "amenities_dining": [
    "Bếp",
    "Bếp nhỏ",
    "Quán bar cạnh bể bơi",
    "Tiện nghi nấu nướng ngoài trời"
  ],
  "nearby_places": [
    {
      "name": "Làng gốm Bát Tràng",
      "type": "Trung Tâm và Khu Mua Sắm",
      "distance_km": 3.9
    },
    {
      "name": "Authentic Bát Tràng - Cửa hàng gốm sứ",
      "type": "Trung Tâm và Khu Mua Sắm",
      "distance_km": 3.92
    },
    {
      "name": "Sân bay Quốc tế Nội Bài",
      "type": "Sân Bay",
      "distance_km": 29.07
    },
    {
      "name": "Sân bay Quốc tế Cát Bi",
      "type": "Sân Bay",
      "distance_km": 83.24
    },
    {
      "name": "Sân bay Thọ Xuân",
      "type": "Sân Bay",
      "distance_km": 131.72
    },
    {
      "name": "Van Don International Airport",
      "type": "Sân Bay",
      "distance_km": 153.69
    },
    {
      "name": "Sân bay Sam Neua",
      "type": "Sân Bay",
      "distance_km": 205.41
    }
  ],
  "image_count": 17,
  "image_urls": [
    "https://pix8.agoda.net/hotelImages/51568479/0/02e9826a7dee65ddf3dc2745865ea67c.jpg?ce=0&s=1024x768",
    "https://pix8.agoda.net/hotelImages/51568479/0/ce551146d9ee4c4464cf30bd91a845a9.jpg?ce=2&s=1024x768",
    "https://pix8.agoda.net/hotelImages/51568479/0/f8320283e9417bf1e602621655bf6ff5.jpg?ce=0&s=1024x768",
    "https://pix8.agoda.net/hotelImages/51568479/0/cc65726731e9963c9f01b1a4ecc11fa9.jpg?ce=2&s=1024x768",
    "https://pix8.agoda.net/hotelImages/51568479/0/97c4588c60f7fa6696e4404604c017ee.jpg?ce=2&s=1024x768",
    "https://pix8.agoda.net/hotelImages/51568479/0/c81e46e205425e1d8d41da5f3b361541.jpg?ce=2&s=1024x768",
    "https://pix8.agoda.net/hotelImages/51568479/0/8b058c27922ed7756b5dbbfcf91c4a04.jpg?ce=2&s=1024x768",
    "https://pix8.agoda.net/hotelImages/51568479/0/38eef2c208aeeec26ce2fb47a80e7968.jpg?ce=2&s=1024x768",
    "https://pix8.agoda.net/hotelImages/51568479/0/9b894c7433b884dae0283f0a2c39b993.jpg?ce=0&s=1024x768",
    "https://pix8.agoda.net/hotelImages/51568479/0/18aa26f4cd7c5ca1b735b4bd69ee89e3.jpg?ce=2&s=1024x768",
    "https://pix8.agoda.net/hotelImages/51568479/0/8b82fdc8c61deefe18762d6941be39bc.jpg?ce=2&s=1024x768",
    "https://pix8.agoda.net/hotelImages/51568479/0/dc5e506b4c4f03570ae9ef9e858655c6.jpg?ce=0&s=1024x768",
    "https://pix8.agoda.net/hotelImages/51568479/0/0584e81cc2279c78be0c49fd8f0d7fdf.jpg?ce=2&s=1024x768",
    "https://pix8.agoda.net/hotelImages/51568479/0/144c3ae5bf11c75179eed3b0cccbfa6e.jpg?ce=0&s=1024x768",
    "https://pix8.agoda.net/hotelImages/51568479/0/deac5baa4790398a337bfa40d8dce0c0.jpg?ce=0&s=1024x768",
    "https://pix8.agoda.net/hotelImages/51568479/0/6ddaa733f63e28e1a73231e43932320b.jpg?ce=0&s=1024x768",
    "https://pix8.agoda.net/hotelImages/51568479/0/caa6600a918b643136bc5372967f6994.png?ce=2&s=1024x768"
  ],
  "images": [
    {
      "url": "https://pix8.agoda.net/hotelImages/51568479/0/02e9826a7dee65ddf3dc2745865ea67c.jpg?ce=0&s=1024x768",
      "caption": "",
      "category": "Cơ sở vật chất"
    },
    {
      "url": "https://pix8.agoda.net/hotelImages/51568479/0/ce551146d9ee4c4464cf30bd91a845a9.jpg?ce=2&s=1024x768",
      "caption": "",
      "category": "Khách sạn"
    },
    {
      "url": "https://pix8.agoda.net/hotelImages/51568479/0/f8320283e9417bf1e602621655bf6ff5.jpg?ce=0&s=1024x768",
      "caption": "",
      "category": "Cơ sở vật chất"
    },
    {
      "url": "https://pix8.agoda.net/hotelImages/51568479/0/cc65726731e9963c9f01b1a4ecc11fa9.jpg?ce=2&s=1024x768",
      "caption": "",
      "category": "Khách sạn"
    },
    {
      "url": "https://pix8.agoda.net/hotelImages/51568479/0/97c4588c60f7fa6696e4404604c017ee.jpg?ce=2&s=1024x768",
      "caption": "",
      "category": "Khách sạn"
    },
    {
      "url": "https://pix8.agoda.net/hotelImages/51568479/0/c81e46e205425e1d8d41da5f3b361541.jpg?ce=2&s=1024x768",
      "caption": "",
      "category": "Khách sạn"
    },
    {
      "url": "https://pix8.agoda.net/hotelImages/51568479/0/8b058c27922ed7756b5dbbfcf91c4a04.jpg?ce=2&s=1024x768",
      "caption": "Hoạt động",
      "category": "Cơ sở vật chất"
    },
    {
      "url": "https://pix8.agoda.net/hotelImages/51568479/0/38eef2c208aeeec26ce2fb47a80e7968.jpg?ce=2&s=1024x768",
      "caption": "Nhà hàng",
      "category": "Ăn uống"
    },
    {
      "url": "https://pix8.agoda.net/hotelImages/51568479/0/9b894c7433b884dae0283f0a2c39b993.jpg?ce=0&s=1024x768",
      "caption": "",
      "category": "Cơ sở vật chất"
    },
    {
      "url": "https://pix8.agoda.net/hotelImages/51568479/0/18aa26f4cd7c5ca1b735b4bd69ee89e3.jpg?ce=2&s=1024x768",
      "caption": "Phòng tập",
      "category": "Cơ sở vật chất"
    },
    {
      "url": "https://pix8.agoda.net/hotelImages/51568479/0/8b82fdc8c61deefe18762d6941be39bc.jpg?ce=2&s=1024x768",
      "caption": "Đồ ăn và thức uống",
      "category": "Ăn uống"
    },
    {
      "url": "https://pix8.agoda.net/hotelImages/51568479/0/dc5e506b4c4f03570ae9ef9e858655c6.jpg?ce=0&s=1024x768",
      "caption": "",
      "category": "Cơ sở vật chất"
    },
    {
      "url": "https://pix8.agoda.net/hotelImages/51568479/0/0584e81cc2279c78be0c49fd8f0d7fdf.jpg?ce=2&s=1024x768",
      "caption": "Khu vực trẻ em",
      "category": "Cơ sở vật chất"
    },
    {
      "url": "https://pix8.agoda.net/hotelImages/51568479/0/144c3ae5bf11c75179eed3b0cccbfa6e.jpg?ce=0&s=1024x768",
      "caption": "",
      "category": "Cơ sở vật chất"
    },
    {
      "url": "https://pix8.agoda.net/hotelImages/51568479/0/deac5baa4790398a337bfa40d8dce0c0.jpg?ce=0&s=1024x768",
      "caption": "",
      "category": "Cơ sở vật chất"
    },
    {
      "url": "https://pix8.agoda.net/hotelImages/51568479/0/6ddaa733f63e28e1a73231e43932320b.jpg?ce=0&s=1024x768",
      "caption": "",
      "category": "Cơ sở vật chất"
    },
    {
      "url": "https://pix8.agoda.net/hotelImages/51568479/0/caa6600a918b643136bc5372967f6994.png?ce=2&s=1024x768",
      "caption": "",
      "category": "Khác"
    }
  ],
  "district": "Đa Tốn",
  "province": "Gia Lâm",
  "city_id": 115695,
  "property_page": "/sunlight-hotel-h51568479/hotel/gia-lam-vn.html",
  "room_grid": {
    "is_sold_out": true,
    "cheapest_price": null,
    "room_count": 0,
    "rooms": []
  },
  "rooms": [],
  "reviews_detail": {
    "score": 8.9,
    "score_text": "Tuyệt vời",
    "review_count": 101,
    "comments_count": 2,
    "grades": [
      {
        "name": "Vị trí",
        "score": 9.5
      },
      {
        "name": "",
        "score": 8.9
      },
      {
        "name": "Độ sạch sẽ",
        "score": 8.0
      },
      {
        "name": "Đáng tiền",
        "score": 8.0
      },
      {
        "name": "Cơ sở vật chất",
        "score": 7.5
      },
      {
        "name": "Dịch vụ",
        "score": 7.0
      }
    ],
    "tags": [
      {
        "tag": "Độ sạch sẽ",
        "mentioned": 1,
        "positive_pct": 0.0
      },
      {
        "tag": "Tiện nghi trong phòng",
        "mentioned": 1,
        "positive_pct": 0.0
      },
      {
        "tag": "Dịch vụ",
        "mentioned": 1,
        "positive_pct": 0.0
      }
    ],
    "word_cloud": [],
    "demographics": [
      {
        "name": "Cặp đôi",
        "count": 1,
        "score": 8.0
      },
      {
        "name": "Khách du lịch một mình",
        "count": 1,
        "score": 10.0
      },
      {
        "name": "Nhóm du khách",
        "count": 2,
        "score": 7.0
      }
    ],
    "sample_comments": [
      {
        "rating": 4.0,
        "rating_text": "Điểm nhận xét",
        "date": "31 tháng 8 2025",
        "check_in": "Tháng 8 năm 2025",
        "text": "Thái độ nhân viên cực kém, bắt cọc 1tr trong khi trước đó đã trả full tiền phòng, khách hỏi thì nói \"chị lên agoda mà thắc mắc\". Phòng ngập ngựa mùi thuốc lá không tan nổi, sàn bẩn, dụng cụ bếp thì không cung cấp, không cho khách nấu nướng trong khi khách thuê căn hộ để sinh hoạt cho tiện nghi. Rất khó chịu với dịch vụ, không bao giờ quay lại.",
        "title": "Chấp nhận được",
        "positives": null,
        "negatives": null,
        "response": null,
        "reviewer_name": "Huyền",
        "reviewer_type": "Nhóm",
        "reviewer_country": "Việt Nam",
        "room_type": ""
      },
      {
        "rating": 8.0,
        "rating_text": "Tuyệt vời",
        "date": "16 tháng 5 2024",
        "check_in": "Tháng 5 năm 2024",
        "text": "They didn't speak english , very hard tó find the apartments",
        "title": "Hard to find",
        "positives": null,
        "negatives": null,
        "response": null,
        "reviewer_name": "Ákos",
        "reviewer_type": "Cặp đôi",
        "reviewer_country": "Slovakia",
        "room_type": "Phòng Có Giường Cỡ King Với Ban Công"
      },
      {
        "review_id": 1018150308,
        "rating": 4.0,
        "rating_text": "Review score",
        "date": "August 31, 2025",
        "check_in": "August 2025",
        "title": "Acceptable",
        "text": "The staff's attitude is extremely poor, they require a deposit of 1 million VND while I had already paid the full amount for the room. When I asked, they said, \"Go ask on Agoda.\" The room was filled with the smell of cigarettes that wouldn't go away, the floor was dirty, kitchen utensils were not provided, and I wasn't allowed to cook even though I rented the apartment for convenience. I was very dissatisfied with the service and will never return.",
        "positives": null,
        "negatives": null,
        "response": null,
        "reviewer_name": "Huyền",
        "reviewer_type": "Group",
        "reviewer_country": "Vietnam",
        "room_type": ""
      },
      {
        "review_id": 805075036,
        "rating": 8.0,
        "rating_text": "Excellent",
        "date": "May 16, 2024",
        "check_in": "May 2024",
        "title": "Hard to find",
        "text": "They didn't speak english , very hard tó find the apartments",
        "positives": null,
        "negatives": null,
        "response": null,
        "reviewer_name": "Ákos",
        "reviewer_type": "Couple",
        "reviewer_country": "Slovakia",
        "room_type": "King Room with Balcony"
      }
    ]
  },
  "rating_overall": 8.9,
  "rating_count": 101,
  "rating_breakdown": {
    "Vị trí": 9.5,
    "Độ sạch sẽ": 8.0,
    "Đáng tiền": 8.0,
    "Cơ sở vật chất": 7.5,
    "Dịch vụ": 7.0
  },
  "secondary": {
    "description_full": "Khám Phá Sự Sang Trọng Tại Sunlight Condotel Hanoi - Địa Điểm 5 Sao Tại Gia Lâm\n\nSunlight Condotel Hanoi là một khách sạn 5 sao đẳng cấp nằm tại trung tâm khu vực Gia Lâm, Việt Nam, mang đến trải nghiệm lưu trú sang trọng và tiện nghi cho mọi du khách. Với thời gian nhận phòng bắt đầu từ 14:00 và trả phòng vào lúc 12:00 trưa, khách hàng có thể thoải mái tận hưởng kỳ nghỉ của mình mà không cần lo lắng về thủ tục. Khách sạn chỉ có một phòng duy nhất, mang lại cảm giác riêng tư và đẳng cấp cho mỗi khách lưu trú.\n\nĐặc biệt, Sunlight Condotel Hanoi có chính sách thân thiện với gia đình, cho phép trẻ em từ 1 đến 2 tuổi ở miễn phí. Đây là lựa chọn lý tưởng cho các gia đình muốn kết hợp sự sang trọng và sự thoải mái trong chuyến đi của mình. Với dịch vụ tuyệt vời và không gian tinh tế, khách sạn chắc chắn sẽ để lại ấn tượng khó quên trong lòng mỗi du khách khi ghé thăm Gia Lâm.\n\nTiện Nghi Giải Trí Đẳng Cấp Tại Sunlight Condotel Hanoi\n\nTại Sunlight Condotel Hanoi, du khách sẽ được trải nghiệm một loạt các tiện ích giải trí đa dạng và phong phú để thư giãn và tận hưởng kỳ nghỉ của mình. Khu vườn xinh đẹp mang lại không gian yên bình, lý tưởng để thư giãn hoặc tận hưởng những buổi sáng sớm trong lành. Ngoài ra, khu vực lounge chung cùng phòng xem TV giúp khách có thể giao lưu và thư giãn cùng nhau sau một ngày khám phá thành phố. Đối với những ai yêu thích giải trí âm nhạc, dịch vụ karaoke sôi động sẽ mang lại những phút giây vui vẻ và gắn kết bên bạn bè và người thân.\n\nKhông chỉ dừng lại ở đó, Sunlight Condotel Hanoi còn cung cấp các tiện ích mua sắm như cửa hàng quà lưu niệm và cửa hàng đặc sản, giúp du khách dễ dàng tìm kiếm những món quà ý nghĩa để tặng người thân. Dịch vụ salon, massage và spa cao cấp mang đến trải nghiệm làm đẹp và thư giãn tuyệt vời, giúp khách lấy lại năng lượng sau những ngày dài di chuyển hoặc công tác. Tất cả những tiện ích này đều nhằm mang đến cho du khách một kỳ nghỉ trọn vẹn, thoải mái và đầy sắc màu tại trung tâm Gia Lâm.\n\nTiện Nghi Thể Thao Đa Dạng Tại Sunlight Condotel Hanoi\n\nTại Sunlight Condotel Hanoi, du khách sẽ được trải nghiệm một loạt các tiện nghi thể thao đẳng cấp để duy trì phong độ và thư giãn sau những giờ phút khám phá thành phố. Khách sạn sở hữu trung tâm thể hình hiện đại, giúp bạn duy trì lối sống năng động và khỏe mạnh. Ngoài ra, các hoạt động thể thao ngoài trời như sân tennis, sân bóng bàn, sân cầu lông và sân mini golf mang đến những trải nghiệm vui vẻ và sôi động cho cả gia đình và nhóm bạn. Đối với những ai yêu thích hoạt động dưới nước, hồ bơi trong nhà và hồ bơi ngoài trời với quầy bar bên hồ là nơi lý tưởng để thư giãn và thưởng thức không khí trong lành.\n\nKhông chỉ dừng lại ở đó, Sunlight Condotel Hanoi còn có sân golf ngay tại chỗ, khu vực câu cá, khu vui chơi nước, và phòng yoga yên tĩnh giúp bạn cân bằng giữa thể chất và tinh thần. Với các tiện ích đa dạng này, du khách có thể dễ dàng lựa chọn hoạt động phù hợp để nâng cao sức khỏe, giải trí hoặc thư giãn, mang lại trải nghiệm hoàn hảo trong suốt kỳ nghỉ của mình.\n\nTiện Nghi Tiện Lợi Tại Sunlight Condotel Hanoi\n\nSunlight Condotel Hanoi mang đến cho khách lưu trú những tiện ích hiện đại và tiện nghi để đảm bảo trải nghiệm thoải mái nhất. Khách hàng có thể tận hưởng dịch vụ Wi-Fi miễn phí trong tất cả các phòng, giúp dễ dàng kết nối và làm việc suốt ngày. Đặc biệt, khách còn được sử dụng dịch vụ check-in và check-out nhanh chóng, tiết kiệm thời gian và thuận tiện cho lịch trình di chuyển. Ngoài ra, khách còn có thể dễ dàng mua sắm tại cửa hàng tiện lợi ngay trong khuôn viên khách sạn hoặc sử dụng dịch vụ giặt ủi hàng ngày để giữ gìn quần áo luôn sạch sẽ và mới mẻ. Đối với những người hút thuốc, Sunlight Condotel Hanoi còn có khu vực hút thuốc riêng biệt, đảm bảo vệ sinh và an toàn cho toàn bộ khách lưu trú.\n\nTiện Nghi Giao Thông Tại Sunlight Condotel Hanoi\n\nTại Sunlight Condotel Hanoi, khách lưu trú sẽ được trải nghiệm dịch vụ đỗ xe tiện lợi và an toàn ngay trong khuôn viên khách sạn. Với khu vực đỗ xe nằm ngay tại chỗ, khách có thể yên tâm về sự thuận tiện trong việc di chuyển và lưu giữ phương tiện của mình. Dịch vụ đỗ xe tự phục vụ giúp khách hàng dễ dàng tiếp cận và sử dụng theo ý muốn của mình, mang lại cảm giác thoải mái và linh hoạt trong suốt kỳ nghỉ.\n\nĐặc biệt, khách lưu trú tại đây còn được hưởng dịch vụ đỗ xe miễn phí, giúp tiết kiệm chi phí và tăng thêm phần tiện nghi cho chuyến đi. Trong trường hợp cần thiết, khách cũng có thể sử dụng các dịch vụ đỗ xe có phí, phù hợp với nhu cầu và lịch trình của từng người. Với hệ thống giao thông thuận tiện và các tiện ích đỗ xe đa dạng, Sunlight Condotel Hanoi cam kết mang lại trải nghiệm lưu trú trọn vẹn, dễ dàng di chuyển và thuận tiện tối đa cho khách hàng.\n\nTiện nghi phòng ốc hiện đại tại Sunlight Condotel Hanoi\n\nTại Sunlight Condotel Hanoi, khách lưu trú sẽ được trải nghiệm không gian nghỉ dưỡng tiện nghi với đầy đủ các thiết bị cao cấp. Phòng có điều hòa không khí giúp duy trì nhiệt độ lý tưởng, cùng với rèm chắn sáng giúp tạo không gian yên tĩnh, thoải mái. Khách còn có thể thư giãn với các bộ phim trong nhà qua hệ thống truyền hình, hoặc tận hưởng không khí trong lành từ ban công hoặc sân thượng riêng biệt.\n\nNgoài ra, các tiện ích như máy sấy tóc, đồ dùng vệ sinh cá nhân, nước khoáng miễn phí, tủ lạnh, và trà, cà phê miễn phí mang đến sự tiện lợi tối đa. Phòng còn có phòng khách riêng biệt, giúp khách có không gian sinh hoạt rộng rãi, thoải mái. Đặc biệt, các bộ đồ tắm, áo choàng tắm sang trọng và các tiện nghi khác sẽ làm cho kỳ nghỉ của bạn thêm phần trọn vẹn, thư giãn.\n\nTiện Nghi Ẩm Thực Tại Sunlight Condotel Hanoi\n\nTại Sunlight Condotel Hanoi, du khách sẽ được trải nghiệm dịch vụ ẩm thực đa dạng và tiện nghi, trong đó nổi bật là các khu vực BBQ hiện đại, lý tưởng để tổ chức những buổi tiệc ngoài trời ấm cúng cùng gia đình hoặc bạn bè. Không khí trong lành và không gian thoáng đãng của khu vực BBQ giúp bạn thưởng thức những món nướng thơm ngon, đậm đà trong khung cảnh thiên nhiên yên bình của Gia Lâm. Ngoài ra, khách sạn còn cung cấp dịch vụ dọn dẹp hàng ngày, đảm bảo không gian luôn sạch sẽ, gọn gàng để du khách có thể hoàn toàn thư giãn và tận hưởng kỳ nghỉ của mình một cách trọn vẹn nhất.\n\nCác Loại Phòng Tại Sunlight Condotel Hanoi - Sự Lựa Chọn Hoàn Hảo Cho Kỳ Nghỉ Của Bạn\n\nTại Sunlight Condotel Hanoi, bạn có thể lựa chọn phòng TWIN rộng 32 mét vuông, được trang bị hai giường đơn phù hợp cho những khách du lịch đi cùng bạn bè hoặc gia đình nhỏ. Phòng TWIN mang đến không gian thoải mái, tiện nghi để bạn thư giãn và tận hưởng kỳ nghỉ của mình một cách trọn vẹn. Mỗi phòng đều được thiết kế tinh tế, mang lại cảm giác ấm cúng và thân thiện, giúp bạn cảm thấy như đang ở nhà ngay trong chuyến đi xa nhà.\n\nKhi đặt phòng qua Agoda, bạn sẽ nhận được mức giá tốt nhất cùng với quy trình đặt phòng nhanh chóng, dễ dàng và không gây phiền hà. Các ưu đãi hấp dẫn này giúp bạn tiết kiệm chi phí và có thêm thời gian để tận hưởng những trải nghiệm tuyệt vời tại Gia Lâm. Đặt phòng ngay hôm nay để đảm bảo chuyến đi của bạn không chỉ trọn vẹn mà còn thuận tiện nhất!\n\nKhám Phá Vùng Đất Đa Tốn - Gia Lâm, Hà Nội\n\nĐa Tốn, một xã thuộc huyện Gia Lâm, Hà Nội, nổi bật với vẻ đẹp bình yên và phong cảnh thiên nhiên tươi đẹp. Nơi đây mang đậm nét truyền thống Việt Nam với những cánh đồng lúa xanh mướt, những con sông nhỏ uốn lượn qua làng quê thanh bình. Du khách có thể tận hưởng không khí trong lành, thư thái và cảm nhận rõ nét nét đẹp của cuộc sống nông thôn chân thực, mộc mạc.\nNgoài ra, Đa Tốn còn gần kề nhiều điểm tham quan hấp dẫn như các làng nghề truyền thống, các chợ địa phương sôi động và những di tích lịch sử nhỏ nhưng ý nghĩa. Vùng đất này còn là nơi lý tưởng để trải nghiệm các hoạt động ngoài trời như đi bộ đường dài, câu cá hoặc thưởng thức ẩm thực đặc sản địa phương. Đến với Đa Tốn, du khách không chỉ được thư giãn mà còn có cơ hội khám phá nét đẹp văn hóa và cuộc sống bình dị nhưng đầy sức sống của vùng quê Hà Nội.\n\nHướng Dẫn Di Chuyển Từ Sân Bay Đến Sunlight Condotel Hanoi Tại Gia Lâm\n\nTừ sân bay Nội Bài, khách du lịch có nhiều lựa chọn để đến với Sunlight Condotel Hanoi tại Đa Tốn, Gia Lâm. Nếu bạn muốn di chuyển nhanh chóng và tiện lợi, dịch vụ taxi hoặc xe đưa đón riêng là lựa chọn hàng đầu, chỉ mất khoảng 30-40 phút tùy vào tình hình giao thông. Bạn có thể dễ dàng bắt taxi ngay tại khu vực nhà ga hoặc đặt dịch vụ xe đưa đón trước để đảm bảo có phương tiện sẵn sàng chờ đón khi bạn đến nơi. Ngoài ra, nếu muốn tiết kiệm hơn, bạn có thể sử dụng các dịch vụ xe buýt liên tỉnh hoặc xe khách, sau đó chuyển sang taxi hoặc xe công cộng để đến địa chỉ mong muốn.\n\nKết hợp các phương tiện công cộng như xe buýt cũng là một lựa chọn phù hợp cho những ai thích khám phá và tiết kiệm chi phí. Từ sân bay Nội Bài, bạn có thể bắt tuyến xe buýt số 86 hoặc 07 đến trung tâm Gia Lâm, rồi tiếp tục di chuyển bằng taxi hoặc xe máy thuê để đến Sunlight Condotel. Dù lựa chọn phương tiện nào, hành trình từ sân bay đến khách sạn đều khá dễ dàng, giúp bạn bắt đầu chuyến đi của mình một cách thuận tiện và thoải mái.\n\nGiá phòng tại Sunlight Condotel Hanoi - Cạnh tranh và hợp lý trong khu vực\n\nSunlight Condotel Hanoi mang đến mức giá phòng vô cùng hấp dẫn, dao động từ 26 đến 50 USD mỗi đêm, phù hợp với ngân sách của nhiều du khách. Với mức giá này, khách hàng có thể tận hưởng không gian nghỉ dưỡng tiện nghi, thoải mái mà không phải lo lắng về chi phí quá cao. Điều đặc biệt là giá phòng của Sunlight Condotel Hanoi hoàn toàn cạnh tranh so với mức trung bình của khu vực Gia Lâm, nơi mà giá phòng khách sạn cũng nằm trong khoảng từ 26 đến 50 USD. Như vậy, du khách có thể yên tâm lựa chọn nơi lưu trú phù hợp với ngân sách, đồng thời trải nghiệm dịch vụ chất lượng cao tại một trong những khu vực đang phát triển của Hà Nội.\n\nĐánh giá tích cực về Sunlight Condotel Hanoi từ khách hàng\n\nSunlight Condotel Hanoi nhận được những đánh giá rất tích cực từ khách hàng, với điểm số tổng thể ấn tượng 9.3 trên nhiều khía cạnh. Khách lưu trú đặc biệt ấn tượng với chất lượng dịch vụ và tiện nghi tại khách sạn, khi các tiện ích hiện đại và đầy đủ mang lại sự hài lòng tối đa. Đặc biệt, mức độ sạch sẽ tại đây đạt điểm tuyệt đối 10.0, thể hiện cam kết của khách sạn trong việc duy trì môi trường trong lành và sạch sẽ cho khách hàng.\n\nVị trí của Sunlight Condotel Hanoi cũng được đánh giá cao, thuận tiện để khám phá các điểm tham quan nổi bật quanh khu vực. Giá trị mà khách sạn mang lại được khách hàng đánh giá rất cao, với điểm số 9.3 cho giá trị, cho thấy đây là lựa chọn hợp lý về mặt tài chính mà vẫn đảm bảo trải nghiệm tốt nhất. Dù có một số điểm cần cải thiện như hiệu suất làm việc của nhân viên, tổng thể, khách hàng đều hài lòng và đánh giá cao chất lượng dịch vụ tại đây, khiến đây trở thành một điểm đến lý tưởng cho chuyến đi của bạn tại Gia Lâm, Hà Nội.",
    "hotel_policy": {
      "childPolicies": [
        {
          "isInfant": true,
          "policy": "Trẻ sơ sinh 0-0 tuổi [bao gồm cả bé 0 tuổi]",
          "description": "Lưu trú miễn phí khi sử dụng giường có sẵn. Lưu ý, nếu quý khách cần cũi em bé, việc này có thể phát sinh thêm phụ phí và phụ thuộc vào tình trạng thực tế."
        },
        {
          "isInfant": false,
          "policy": "Trẻ em 1-2 tuổi [bao gồm cả bé 2 tuổi]",
          "description": "Phải sử dụng giường phụ"
        }
      ],
      "extrabedPolicies": [
        {
          "type": 1,
          "description": "Giường phụ tùy thuộc vào loại phòng bạn chọn, xin vui lòng kiểm tra thông tin phòng để biết thêm chi tiết."
        }
      ],
      "policyNotes": [
        "Tiền đặt cọc bắt buộc khi nhận phòng (cho mỗi lần lưu trú):\n• Phòng ngủ hạng sang Queen Deluxe và phòng Twin: 1.000.000 VND\n• Căn hộ 2 phòng ngủ: 2.000.000 VND\n• Căn hộ 3 phòng ngủ: 2.500.000 VND\n• Phòng penthouse Duplex: 3.000.000 VND"
      ],
      "hideAutomatedChildPolicyText": false,
      "extraBedAge": 1,
      "hasBcomChildPolicy": false
    },
    "other_policies": [],
    "dateless_rooms_count": 0,
    "dateless_rooms": []
  },
  "description_short": "Đỗ xe và Wi-Fi luôn miễn phí, vì vậy quý khách có thể giữ liên lạc, đến và đi tùy ý. Nằm ở vị trí trung tâm tại Đa Tốn của Gia Lâm, chỗ nghỉ này đặt quý khách ở gần các điểm thu hút và tùy chọn ăn uống thú vị. Được xếp hạng 5 sao, chỗ nghỉ chất lượng cao này cho phép khách nghỉ sử dụng bể bơi trong nhà, mát-xa và bể bơi ngoài trời ngay trong khuôn viên.",
  "activities": [
    {
      "activity_id": 1526247,
      "title": "eSIM Việt Nam | Viettel 5G | Tốc độ 5G nhanh nhất",
      "description": "Kết nối internet tốc độ cao tại Việt Nam với eSIM Viettel 5G, giải pháp linh hoạt cho mọi nhu cầu liên lạc và làm việc.\n\n- Truy cập dữ liệu tốc độ cao 5GB mỗi ngày thông qua mạng 4G/5G của Viettel\n- P",
      "review_score": 4.5,
      "review_count": 159,
      "price": {
        "currency": "VND",
        "display": {
          "perBook": {
            "displayType": "BOOK",
            "quantity": 1,
            "total": {
              "allInclusive": {
                "chargeTotal": 171933.0,
                "crossedOut": 215903.0
              }
            }
          }
        }
      }
    },
    {
      "activity_id": 1649522,
      "title": "Dịch vụ Fast Track tại sân bay Tân Sơn Nhất",
      "description": "Trải nghiệm dịch vụ Fast Track tại sân bay Tân Sơn Nhất để tối ưu hóa thời gian khi nhập cảnh vào Thành phố Hồ Chí Minh.\n\n- Nhân viên chuyên nghiệp đón tiếp trực tiếp ngay khi bạn vừa hạ cánh\n- Hỗ trợ",
      "review_score": 4.3,
      "review_count": 152,
      "price": {
        "currency": "VND",
        "display": {
          "perBook": {
            "displayType": "BOOK",
            "quantity": 1,
            "total": {
              "allInclusive": {
                "chargeTotal": 452649.0,
                "crossedOut": 506319.0
              }
            }
          }
        }
      }
    },
    {
      "activity_id": 1289739,
      "title": "Vé vào cổng Công viên Chủ đề VinWonders Cửa Hội",
      "description": "Khám phá VinWonders Cửa Hội, tổ hợp giải trí sôi động tại miền Trung Việt Nam với những trải nghiệm đa dạng từ vui chơi đến tâm linh.\n\n- Trải nghiệm hệ thống cáp treo vượt biển đầu tiên và duy nhất tạ",
      "review_score": 5.0,
      "review_count": 1,
      "price": {
        "currency": "VND",
        "display": {
          "perBook": {
            "displayType": "BOOK",
            "quantity": 1,
            "total": {
              "allInclusive": {
                "chargeTotal": 87446.0,
                "crossedOut": 100053.0
              }
            }
          }
        }
      }
    },
    {
      "activity_id": 1563604,
      "title": "VOYE Asia eSIM | 16 Quốc gia & Vùng lãnh thổ Châu Á",
      "description": "Sử dụng eSIM Asia của VOYE để kết nối dữ liệu tại 16 quốc gia và vùng lãnh thổ châu Á mà không cần thay nhiều SIM hay dùng VPN.\n\n- Tặng thêm 100MB để kiểm tra eSIM ngay tại quốc gia sở tại\n- Truy cập",
      "review_score": 3.3,
      "review_count": 71,
      "price": {
        "currency": "VND",
        "display": {
          "perBook": {
            "displayType": "BOOK",
            "quantity": 1,
            "total": {
              "allInclusive": {
                "chargeTotal": 23012.0,
                "crossedOut": 30542.0
              }
            }
          }
        }
      }
    },
    {
      "activity_id": 1577433,
      "title": "Voucher Quà Tặng Xanh SM - Việt Nam",
      "description": "Sản phẩm này chỉ áp dụng tại thị trường Việt Nam.\nGreen SM là thương hiệu gọi xe hoàn toàn bằng điện đầu tiên tại Việt Nam, cung cấp các trải nghiệm di chuyển độc đáo bao gồm Gree",
      "review_score": 0.0,
      "review_count": 0,
      "price": {
        "currency": "VND",
        "display": {
          "perBook": {
            "displayType": "BOOK",
            "quantity": 1,
            "total": {
              "allInclusive": {
                "chargeTotal": 49226.0,
                "crossedOut": 50026.0
              }
            }
          }
        }
      }
    },
    {
      "activity_id": 1649514,
      "title": "Dịch vụ làm thủ tục nhanh Nội Bài - Thủ tục xuất nhập cảnh, hướng dẫn viên chu đáo và làn ưu tiên (kiểm tra hành lý & hải quan) - Hà Nội, Việt Nam",
      "description": "Chào đón chu đáo: Khi đến sân bay, bạn sẽ được đội ngũ nhân viên chuyên nghiệp và tận tâm của chúng tôi chào đón. Không còn phải tìm kiếm quầy hay cảm thấy lạc lõng giữa đám đông - đội ngũ của chún",
      "review_score": 4.3,
      "review_count": 59,
      "price": {
        "currency": "VND",
        "display": {
          "perBook": {
            "displayType": "BOOK",
            "quantity": 1,
            "total": {
              "allInclusive": {
                "chargeTotal": 368381.0,
                "crossedOut": 412059.0
              }
            }
          }
        }
      }
    },
    {
      "activity_id": 1562173,
      "title": "eSIM Việt Nam Mobifone 5G Trả Trước - Hỗ Trợ Gọi & SMS",
      "description": "- Khám phá kết nối tốc độ cao với eSIM Việt Nam, tận hưởng internet 5G mạnh mẽ từ Mobifone trên khắp các thành phố lớn.\n- Chọn gói cước eSIM phù hợp với lịch trình du lịch Việt Nam của bạn, với các lự",
      "review_score": 2.5,
      "review_count": 12,
      "price": {
        "currency": "VND",
        "display": {
          "perBook": {
            "displayType": "BOOK",
            "quantity": 1,
            "total": {
              "allInclusive": {
                "chargeTotal": 68325.0,
                "crossedOut": 85571.0
              }
            }
          }
        }
      }
    },
    {
      "activity_id": 1073884,
      "title": "E-visa Việt Nam - Xin cấp (Một/Nhiều lần) & Đến sân bay",
      "description": "* Khám phá dịch vụ Thị thực khi đến Việt Nam (Visa On Arrival) dành cho du khách không đủ điều kiện xin E-visa Việt Nam hoặc gặp khó khăn trong quá trình nộp hồ sơ.\n* Tận hưởng quá trình xử lý nha",
      "review_score": 4.8,
      "review_count": 43,
      "price": {
        "currency": "VND",
        "display": {
          "perBook": {
            "displayType": "BOOK",
            "quantity": 1,
            "total": {
              "allInclusive": {
                "chargeTotal": 511204.0,
                "crossedOut": 612954.0
              }
            }
          }
        }
      }
    },
    {
      "activity_id": 1562703,
      "title": "Trải Nghiệm Mát Xa Spa Hà Nội",
      "description": "* Đắm mình vào trải nghiệm spa và massage tại Hà Nội, nơi bạn có thể khám phá các liệu pháp chăm sóc sức khỏe đa dạng.\n* Từ liệu trình thư giãn cơ bản đến các phương pháp trị liệu chuyên sâu, trun",
      "review_score": 4.9,
      "review_count": 136,
      "price": {
        "currency": "VND",
        "display": {
          "perBook": {
            "displayType": "BOOK",
            "quantity": 1,
            "total": {
              "allInclusive": {
                "chargeTotal": 105218.0,
                "crossedOut": 117694.0
              }
            }
          }
        }
      }
    },
    {
      "activity_id": 1554111,
      "title": "Dịch Vụ Làm Thủ Tục Nhanh Sân Bay Tân Sơn Nhất - Đón Tiễn Ưu Tiên",
      "description": "* Tận hưởng dịch vụ Fast Track tại Sân bay Quốc tế Tân Sơn Nhất, với sự hỗ trợ ưu tiên cho các thủ tục xuất nhập cảnh và hải quan.\n* Được chào đón và hộ tống bởi nhân viên riêng tại sân bay, mang",
      "review_score": 0.0,
      "review_count": 0,
      "price": {
        "currency": "VND",
        "display": {
          "perBook": {
            "displayType": "BOOK",
            "quantity": 1,
            "total": {
              "allInclusive": {
                "chargeTotal": 420872.0,
                "crossedOut": 470774.0
              }
            }
          }
        }
      }
    }
  ],
  "faq": [],
  "suitable_for": [
    "Cặp đôi",
    "Khách du lịch một mình",
    "Nhóm du khách"
  ],
  "view_types": [],
  "tags": [
    "Bàn tiếp tân [24 giờ]",
    "Cặp đôi",
    "Dọn phòng hằng ngày",
    "Khách du lịch một mình",
    "Nhóm du khách",
    "Nhận/trả phòng [nhanh]",
    "Quán bar cạnh bể bơi",
    "Rút tiền mặt",
    "Thích hợp cho các hoạt động",
    "Wi-Fi miễn phí trong tất cả các phòng!"
  ],
  "embedding_text": "Sunlight Condotel Hà Nội (Sunlight Condotel Hanoi) - khách sạn 5.0 sao tại Gia Lâm.\nĐịa chỉ: Masteri Waterfront M3, Vinhomes Ocean Park, Đa Tốn, Gia L m, Hanoi, Vietnam, Đa Tốn, Gia Lâm, Việt Nam.\nĐỗ xe và Wi-Fi luôn miễn phí, vì vậy quý khách có thể giữ liên lạc, đến và đi tùy ý. Nằm ở vị trí trung tâm tại Đa Tốn của Gia Lâm, chỗ nghỉ này đặt quý khách ở gần các điểm thu hút và tùy chọn ăn uống thú vị. Được xếp hạng 5 sao, chỗ nghỉ chất lượng cao này cho phép khách nghỉ sử dụng bể bơi trong nhà, mát-xa và bể bơi ngoài trời ngay trong khuôn viên.\nTiện ích: Bi-a, Bàn tiếp tân [24 giờ], Bãi chơi bowling, Bãi đỗ xe [gần bên], Bãi đỗ xe [miễn phí], Bãi đỗ xe [tại chỗ], Bảo vệ [24 giờ], Bếp, Bếp nhỏ, Bể bơi, Bể bơi [trong nhà], Bể bơi [trẻ em], Bể bơi có tầm nhìn, Bể bơi [ngoài trời], Bệnh xá, CCTV trong khu vực chung, CLB trẻ em, Câu cá, Có cung cấp hóa đơn, Công viên nước, Cửa hàng, Cửa hàng quà tặng/quà lưu niệm, Cửa hàng tạp hóa, Dịch vụ bưu chính, Dịch vụ thanh toán không sử dụng tiền mặt, Dọn phòng hằng ngày, Giải trí trong khuôn viên, Hành lang ngoài, Hộp vệ sinh cho mèo, Internet.\nĐiểm đánh giá 8.9/10 dựa trên 101 đánh giá.\nKhách hay nhắc đến: Độ sạch sẽ, Tiện nghi trong phòng, Dịch vụ.\nGần: Làng gốm Bát Tràng, Authentic Bát Tràng - Cửa hàng gốm sứ, Sân bay Quốc tế Nội Bài, Sân bay Quốc tế Cát Bi, Sân bay Thọ Xuân, Van Don International Airport.",
  "_sources_captured": [
    "activities",
    "details",
    "faq",
    "reviews",
    "rooms",
    "secondary"
  ]
}